odoo/addons/stock_picking_batch_print_invoices/README.rst
odoo/addons/stock_picking_batch_print_invoices/__init__.py
odoo/addons/stock_picking_batch_print_invoices/__manifest__.py
odoo/addons/stock_picking_batch_print_invoices/i18n/es.po
odoo/addons/stock_picking_batch_print_invoices/i18n/it.po
odoo/addons/stock_picking_batch_print_invoices/i18n/stock_picking_batch_print_invoices.pot
odoo/addons/stock_picking_batch_print_invoices/models/__init__.py
odoo/addons/stock_picking_batch_print_invoices/models/stock_picking_batch.py
odoo/addons/stock_picking_batch_print_invoices/models/stock_picking_type.py
odoo/addons/stock_picking_batch_print_invoices/readme/CONFIGURE.md
odoo/addons/stock_picking_batch_print_invoices/readme/CONTEXT.md
odoo/addons/stock_picking_batch_print_invoices/readme/CONTRIBUTORS.md
odoo/addons/stock_picking_batch_print_invoices/readme/DESCRIPTION.md
odoo/addons/stock_picking_batch_print_invoices/readme/USAGE.md
odoo/addons/stock_picking_batch_print_invoices/static/description/icon.png
odoo/addons/stock_picking_batch_print_invoices/static/description/index.html
odoo/addons/stock_picking_batch_print_invoices/tests/__init__.py
odoo/addons/stock_picking_batch_print_invoices/tests/test_batch_print_invoices.py
odoo/addons/stock_picking_batch_print_invoices/views/report_picking_batch_print_invoices.xml
odoo/addons/stock_picking_batch_print_invoices/views/stock_picking_batch_views.xml
odoo/addons/stock_picking_batch_print_invoices/views/stock_picking_type_views.xml
odoo_addon_stock_picking_batch_print_invoices-18.0.1.0.1.dist-info/METADATA
odoo_addon_stock_picking_batch_print_invoices-18.0.1.0.1.dist-info/WHEEL
odoo_addon_stock_picking_batch_print_invoices-18.0.1.0.1.dist-info/top_level.txt
odoo_addon_stock_picking_batch_print_invoices-18.0.1.0.1.dist-info/RECORD
